<?xml version="1.0" encoding="utf-8" ?>
<dwsync>
<file name="dietro-min.jpg" server="D:/xampp/htdocs/palazzoReale/" local="131704619279052290" remote="131704619270000000" Dst="2" />
<file name="letto-new-min.jpg" server="D:/xampp/htdocs/palazzoReale/" local="131704619242418435" remote="131704619240000000" Dst="2" />
<file name="base-2.png" server="D:/xampp/htdocs/palazzoReale/" local="131704619300168631" remote="131704619300000000" Dst="2" />
<file name="icona-2.png" server="D:/xampp/htdocs/palazzoReale/" local="131704619253484555" remote="131704619250000000" Dst="2" />
<file name="english.png" server="D:/xampp/htdocs/palazzoReale/" local="131704619256110456" remote="131704619250000000" Dst="2" />
<file name="logo-scuola-2.png" server="D:/xampp/htdocs/palazzoReale/" local="131704619158354073" remote="131704619150000000" Dst="2" />
<file name="palazzo-2.svg" server="D:/xampp/htdocs/palazzoReale/" local="131704619143559438" remote="131704619140000000" Dst="2" />
<file name="PIANTINA-3-1.png" server="D:/xampp/htdocs/palazzoReale/" local="131704619325938487" remote="131704619320000000" Dst="2" />
<file name="chiusura.svg" server="D:/xampp/htdocs/palazzoReale/" local="131704619282506865" remote="131704619280000000" Dst="2" />
<file name="indietro.svg" server="D:/xampp/htdocs/palazzoReale/" local="131704619249038566" remote="131704619240000000" Dst="2" />
<file name="luogo.svg" server="D:/xampp/htdocs/palazzoReale/" local="131704619147735557" remote="131704619140000000" Dst="2" />
<file name="telefono.svg" server="D:/xampp/htdocs/palazzoReale/" local="131704619107953829" remote="131704619100000000" Dst="2" />
<file name="email.svg" server="D:/xampp/htdocs/palazzoReale/" local="131704619256891907" remote="131704619250000000" Dst="2" />
<file name="logo.svg" server="D:/xampp/htdocs/palazzoReale/" local="131704619147695448" remote="131704619140000000" Dst="2" />
<file name="logo-facebook.svg" server="D:/xampp/htdocs/palazzoReale/" local="131704619162053896" remote="131704619160000000" Dst="2" />
<file name="twitter-logo.svg" server="D:/xampp/htdocs/palazzoReale/" local="131704619098789459" remote="131704619090000000" Dst="2" />
</dwsync>